xy_django_app_account/__init__.py
xy_django_app_account/aabstracts.py
xy_django_app_account/abstracts.py
xy_django_app_account/admin.py
xy_django_app_account/apps.py
xy_django_app_account/models.py
xy_django_app_account/serializers.py
xy_django_app_account/tests.py
xy_django_app_account/views.py
xy_django_app_account/__pycache__/__init__.cpython-311.pyc
xy_django_app_account/__pycache__/abstracts.cpython-311.pyc
xy_django_app_account/__pycache__/models.cpython-311.pyc
xy_django_app_account/migrations/__init__.py
xy_django_app_account-1.0.4.dist-info/LICENSE
xy_django_app_account-1.0.4.dist-info/METADATA
xy_django_app_account-1.0.4.dist-info/WHEEL
xy_django_app_account-1.0.4.dist-info/top_level.txt
xy_django_app_account-1.0.4.dist-info/RECORD
